ts_train/__init__.py
ts_train/data.py
ts_train/deepdata.py
ts_train/deeputils.py
ts_train/sysutils.py
ts_train-0.2.dist-info/LICENSE
ts_train-0.2.dist-info/METADATA
ts_train-0.2.dist-info/WHEEL
ts_train-0.2.dist-info/top_level.txt
ts_train-0.2.dist-info/RECORD
