Metadata-Version: 2.1
Name: ts-train
Version: 0.2
Summary: Time-Series Handling for Machine Learning Tasks
Home-page: https://minesh1291.github.io/ts-train
Author: Minesh A. Jethva
Author-email: minesh.1291@gmail.com
License: MIT License
Platform: UNKNOWN
Requires-Dist: numpy
Requires-Dist: pandas
Requires-Dist: scipy
Requires-Dist: opencv-python
Requires-Dist: sklearn
Requires-Dist: tslearn
Requires-Dist: tsfresh
Requires-Dist: dtw
Requires-Dist: fastdtw
Requires-Dist: dtaidistance
Requires-Dist: kneed
Requires-Dist: matplotlib
Requires-Dist: seaborn
Requires-Dist: tqdm
Requires-Dist: arrow
Requires-Dist: recommonmark
Requires-Dist: sphinx-rtd-theme
